redwing_vector
