Metadata-Version: 2.1
Name: redwing-vector
Version: 0.1.2
Summary: Python client to interface with Redwing Vector gRPC Service.
Home-page: https://github.com/redwing-os/client/tree/master/python
Author: Hello Redwing
Author-email: hello@redwing.ai
Classifier: Programming Language :: Python :: 3
Classifier: License :: OSI Approved :: MIT License
Classifier: Operating System :: OS Independent
Requires-Python: >=3.6
License-File: LICENSE
